Workbook

Sheet Rates
B2: Project summary
B3: Approved PJD
B4: Project Lead
B5: Project Manager | C5: Tasha Rockliff
B6: ProgramArea Manager | C6: Insert name
B7: Links to task specifications | C7: Insert link(s) | BA7: =((D7*'Project Overview'!'Project Overview'!42:42D42)+(E7*'Project Overview'!D23)+(F7*'Project Overview'!D24))*1.4
B8: Total person resource hours
B9: Total capital spend
C11: Cost.cat | D11: FY25/26 | E11: FY26/27 | F11: FY27/28 | G11: FY28/29 | H11: Overhead Rate | I11: 1.4
C12: UKA1 | D12: 17.32 | E12: =D12*1.04 -> 18.0128 | F12: =E12*1.04 -> 18.733312 | G12: =F12*1.04 -> 19.482644
C13: UKA2 | D13: 38.85 | E13: =D13*1.04 -> 40.404 | F13: =E13*1.04 -> 42.02016 | G13: =F13*1.04 -> 43.700966
C14: UKL1 | D14: 26.43 | E14: =D14*1.04 -> 27.4872 | F14: =E14*1.04 -> 28.586688 | G14: =F14*1.04 -> 29.730156
C15: UKL2 | D15: 26.43 | E15: =D15*1.04 -> 27.4872 | F15: =E15*1.04 -> 28.586688 | G15: =F15*1.04 -> 29.730156
C16: UKL3 | D16: 30.85 | E16: =D16*1.04 -> 32.084 | F16: =E16*1.04 -> 33.36736 | G16: =F16*1.04 -> 34.702054
C17: UKL4 | D17: 38.75 | E17: =D17*1.04 -> 40.3 | F17: =E17*1.04 -> 41.912 | G17: =F17*1.04 -> 43.58848
C18: UKL5 | D18: 48.03 | E18: =D18*1.04 -> 49.9512 | F18: =E18*1.04 -> 51.949248 | G18: =F18*1.04 -> 54.027218
C19: UKL6 | D19: 62.14 | E19: =D19*1.04 -> 64.6256 | F19: =E19*1.04 -> 67.210624 | G19: =F19*1.04 -> 69.899049
C20: UKL7 | D20: 74.05 | E20: =D20*1.04 -> 77.012 | F20: =E20*1.04 -> 80.09248 | G20: =F20*1.04 -> 83.296179 | I20: Estimate F and H as halfway between grades
C21: UKL8 | D21: 104.9 | E21: =D21*1.04 -> 109.096 | F21: =E21*1.04 -> 113.45984 | G21: =F21*1.04 -> 117.99823 | I21: FY25/26 | J21: FY26/27 | K21: FY27/28 | L21: FY28/29 | N21: 26/27
A22: 22 | B22: UKM3 | C22: UKM3 | D22: 35.29 | E22: =D22*1.04 -> 36.7016 | F22: =E22*1.04 -> 38.169664 | G22: =F22*1.04 -> 39.696451 | H22: UKAXF | I22: =(D23+D24)/2 -> 47.205 | J22: =(E23+E24)/2 -> 49.0932 | K22: =(F23+F24)/2 -> 51.056928 | L22: =(G23+G24)/2 -> 53.099205 | M22: UKAXF | N22: I22
A23: 23 | B23: UKM4 | C23: UKM4 | D23: 40.4 | E23: =D23*1.04 -> 42.016 | F23: =E23*1.04 -> 43.69664 | G23: =F23*1.04 -> 45.444506 | H23: UKAXH | I23: =(D25+D24)/2 -> 60.785 | J23: =(E25+E24)/2 -> 63.2164 | K23: =(F25+F24)/2 -> 65.745056 | L23: =(G25+G24)/2 -> 68.374858 | M23: UKAXH | N23: I23
A24: 24 | B24: UKM5 | C24: UKM5 | D24: 54.01 | E24: =D24*1.04 -> 56.1704 | F24: =E24*1.04 -> 58.417216 | G24: =F24*1.04 -> 60.753905 | AL24: =(Rates!AK24*Rates!D22) -> 0
A25: 25 | B25: UKM6 | C25: UKM6 | D25: 67.56 | E25: =D25*1.04 -> 70.2624 | F25: =E25*1.04 -> 73.072896 | G25: =F25*1.04 -> 75.995812 | H25: Year In Industry | J25: =23810/1575 -> 15.11746 | K25: =J25*1.04 -> 15.722159 | L25: =K25*1.04 -> 16.351045
C26: UKM7 | D26: 88.78 | E26: =D26*1.04 -> 92.3312 | F26: =E26*1.04 -> 96.024448 | G26: =F26*1.04 -> 99.865426 | J26: Year in Industry = 23,810
C27: UKMS | D27: 52.67 | E27: =D27*1.04 -> 54.7768 | F27: =E27*1.04 -> 56.967872 | G27: =F27*1.04 -> 59.246587
C28: UKS3 | D28: 46.7 | E28: =D28*1.04 -> 48.568 | F28: =E28*1.04 -> 50.51072 | G28: =F28*1.04 -> 52.531149
C29: UKS4 | D29: 54 | E29: =D29*1.04 -> 56.16 | F29: =E29*1.04 -> 58.4064 | G29: =F29*1.04 -> 60.742656
C30: UKT1 | D30: 23.14 | E30: =D30*1.04 -> 24.0656 | F30: =E30*1.04 -> 25.028224 | G30: =F30*1.04 -> 26.029353
C31: RU01 | D31: 11.5 | E31: =D31*1.04 -> 11.96 | F31: =E31*1.04 -> 12.4384 | G31: =F31*1.04 -> 12.935936
C32: RU02 | D32: 14.75 | E32: =D32*1.04 -> 15.34 | F32: =E32*1.04 -> 15.9536 | G32: =F32*1.04 -> 16.591744
C33: RU03 | D33: 16.5 | E33: =D33*1.04 -> 17.16 | F33: =E33*1.04 -> 17.8464 | G33: =F33*1.04 -> 18.560256
C34: RU04 | D34: 19.25 | E34: =D34*1.04 -> 20.02 | F34: =E34*1.04 -> 20.8208 | G34: =F34*1.04 -> 21.653632
C35: RU05 | D35: 21.5 | E35: =D35*1.04 -> 22.36 | F35: =E35*1.04 -> 23.2544 | G35: =F35*1.04 -> 24.184576
C36: RU06 | D36: 23.75 | E36: =D36*1.04 -> 24.7 | F36: =E36*1.04 -> 25.688 | G36: =F36*1.04 -> 26.71552
C37: RU07 | D37: 26.5 | E37: =D37*1.04 -> 27.56 | F37: =E37*1.04 -> 28.6624 | G37: =F37*1.04 -> 29.808896
C38: RU08 | D38: 29 | E38: =D38*1.04 -> 30.16 | F38: =E38*1.04 -> 31.3664 | G38: =F38*1.04 -> 32.621056
... C87: IND26 | D87: 125 | E87: =D87*1.04 -> 130 | F87: =E87*1.04 -> 135.2 | G87: =F87*1.04 -> 140.608

Sheet June 26 - UKAEA
B1: Project Dashboard- WON 13875-1000
B4: Month | D4: Forecasted Hours | X4: Forcasted Spend | Z4: Annual Budget | AB4: Actual Spend | AD4: Total Project Cost - Overview
D5: Lloyd Fletcher | E5: Joel Hirst | F5: Joel Hirst | G5: Wiera Bielajewa | H5: Christopher Dawson | I5: Adel Tayeb | J5: Nell Morris | K5: Rory Spencer | L5: Megan Sampson | M5: Alexander Marsh | N5: John Charlton | O5: FC - Total | P5: Rushavya Naidu | Q5: Lucas Pigott | R5: Student 1 | S5: Student 2 | T5: Total PhD Cost | U5: Travel | V5: External Spend | X5: UKAEA Resource Spend ONLY | Y5: UKAEA Forecast Spend | Z5: UKAEA Annual Budget | AA5: Variance from Budget | AB5: Actual Spend to date
B6: Grade | D6: UKAXI | E6: UKAXE | F6: UKAXG | G6: UKAXE | H6: UKAXE | I6: UKM5 | J6: UKL3 | K6: UKM5 | L6: UKM4 | M6: UKM4 | N6: UKM4 | P6: PhD Student
B7: FTE | D7: 0.3 | E7: 0 | F7: 0 | G7: 0 | H7: 0 | I7: 0.9 | J7: 0 | K7: 0 | L7: 0.2 | M7: 1 | N7: 0
B8: FY24/25 | D8: 24 | E8: 0 | F8: 0 | G8: 0 | H8: 0 | I8: 948 | J8: 0 | K8: 0 | L8: 0 | M8: 809 | N8: 0 | O8: =SUM(D8:N8) -> 1781 | T8: =SUM(P8:S8) -> 0 | U8: 627 | V8: 215 | X8: 0 | Y8: 0 | Z8: 0 | AB8: 95819.57 | AD8: Project Budget
B9: FY25/26 | D9: 1091 | E9: 949 | F9: 0 | G9: 780 | H9: 0 | I9: 957 | J9: 10 | K9: 58 | L9: 358 | M9: 1393 | N9: 251 | O9: =SUM(D9:N9) -> 5847 | P9: 7778 | Q9: 8072 | R9: 0 | S9: 0 | T9: =SUM(P9:S9) -> 15850 | U9: 4370 | V9: 27014 | X9: 0 | Y9: 0 | Z9: 300000 | AB9: 268870.79
B10: FY26/27 | D10: =1575*0.3 -> 472.5 | E10: 0 | F10: 0 | G10: 0 | H10: 0 | I10: =1575*0.9 -> 1417.5 | J10: 0 | K10: 0 | L10: =1575*0.2 -> 315 | M10: =1575 -> 1575 | N10: 0 | O10: =SUM(D10:N10) -> 3780 | P10: =7778+7907 -> 15685 | Q10: =8072+8306 -> 16378 | R10: =15849/2 -> 7924.5 | S10: =15849/2 -> 7924.5 | T10: =SUM(P10:S10) -> 47912 | U10: 18000 | V10: 47911 | X10: =(($D10*Rates!$E$25)+(($E10+$G10+$H10+K10+L10+M10)*Rates!$E$23)+(($F10+H10+J10)*Rates!$E$24)*Rates!$I$11) -> 112609.22 | Y10: =X10+T10+U10+V10 -> 226432.22 | Z10: 381973.39 | AA10: =Z10-Y10 -> 155541.17 | AB10: 30849.55 | AD10: 1255259.7
B11: FY27/28 | D11: =1575*0.3 -> 472.5 | E11: 0 | F11: 0 | G11: 0 | H11: 0 | I11: =1575*0.9 -> 1417.5 | J11: 0 | K11: 0 | L11: =1575*0.2 -> 315 | M11: =1575 -> 1575 | N11: 0 | O11: =SUM(D11:N11) -> 3780 | P11: =7907+8038.25 -> 15945.25 | Q11: =8548+8306 -> 16854 | R11: =(15849/2)+(16212/2) -> 16030.5 | S11: =(15849/2)+(16212/2) -> 16030.5 | T11: =SUM(P11:S11) -> 64860.25 | U11: 18000 | V11: 64860 | X11: =(($D11*Rates!$F$25)+(($E11+$G11+$H11+K11+L11+M11)*Rates!$F$23)+(($F11+H11+J11)*Rates!$F$24)*Rates!$I$11) -> 117113.59 | Y11: =X11+T11+U11+V11 -> 264833.84 | Z11: 381973.39 | AA11: =Z11-Y11 -> 117139.55
B12: FY28/29 | D12: =(1575*0.3)/2 -> 236.25 | E12: 0 | F12: 0 | G12: 0 | H12: 0 | I12: =(1575*0.9)/2 -> 708.75 | J12: 0 | K12: 0 | L12: =(1575*0.2)/2 -> 157.5 | M12: =1575/2 -> 787.5 | N12: 0 | O12: =SUM(D12:N12) -> 1890 | P12: =(8038+8172.25)/2 -> 8105.125 | Q12: =(8548+8800)/2 -> 8674 | R12: =(16212+16587)/2 -> 16399.5 | S12: =(16212+16587)/2 -> 16399.5 | T12: =SUM(P12:S12) -> 49578.125 | U12: 9000 | V12: 33106 | X12: =(($D12*Rates!$G$25)+(($E12+$G12+$H12+K12+L12+M12)*Rates!$G$23)+(($F12+H12+J12)*Rates!$G$24)*Rates!$I$11) -> 60899.068 | Y12: =X12+T12+U12+V12 -> 152583.19 | Z12: 95493.35 | AA12: =Z12-Y12 -> -57089.843 | AD12: Forecast Cost at Completion
B14: FAC | D14: =SUM(D8:D13) -> 2296.25 | E14: =SUM(E8:E13) -> 949 | F14: =SUM(F8:F13) -> 0 | G14: =SUM(G8:G13) -> 780 | H14: =SUM(H8:H13) -> 0 | I14: =SUM(I8:I13) -> 5448.75 | J14: =SUM(J8:J13) -> 10 | K14: =SUM(K8:K13) -> 58 | ... V14: =SUM(V8:V13) -> 173106 | X14: =SUM(X8:X12) -> 290621.89 | Y14: =SUM(Y8:Y12) -> 643849.26 | Z14: =SUM(Z8:Z12) -> 1159440.1 | AB14: =SUM(AB8:AB13) -> 395539.91 | AD14: =(Y10-AB10)+Y11+Y12+AB14 -> 1008539.6

Sheet UKAEA
B1: Project Dashboard- WON 13875-1000
B4: Month | D4: Forecasted Hours | AB4: Forcasted Spend | AD4: Annual Budget | AF4: Actual Spend | AH4: Total Project Cost - Overview
D5: Lloyd Fletcher | E5: Joel Hirst | F5: Joel Hirst | G5: Wiera Bielajewa | H5: Wiera Bielajewa | I5: Adel Tayeb | J5: Adel Tayeb | K5: Rob Hamill | L5: Graduates | M5: Year in Industry | N5: Nell Morris | O5: Rory Spencer | P5: Megan Sampson | Q5: Alexander Marsh | R5: John Charlton | S5: FC - Total | T5: Rushavya Naidu | U5: Lucas Pigott | V5: Student 1 | W5: Student 2 | X5: Total PhD Cost | Y5: Travel | Z5: External Spend | AB5: UKAEA Resource Spend ONLY | AC5: UKAEA Forecast Spend | AD5: UKAEA Annual Budget | AE5: Variance from Budget | AF5: Actual Spend to date
B6: Grade | D6: UKAXI | E6: UKAXE | F6: UKAXG | G6: UKAXE | H6: UKAXF | I6: UKM5 | J6: UKAXH | K6: UKAXF | L6: UKL3 | M6: - | N6: UKL3 | O6: UKM5 | P6: UKM4 | Q6: UKM4 | R6: UKM4 | T6: PhD Student
B7: FTE | D7: 0.3 | E7: 0 | F7: 0 | G7: 0 | H7: 0 | I7: 0.9 | J7: 0.9 | K7: 1 | L7: 1 | M7: 1 | N7: 0 | O7: 0 | P7: 0.2 | Q7: 1 | R7: 0
B8: FY24/25 | D8: 24 | E8: 0 | F8: 0 | G8: 0 | H8: 0 | I8: 948 | J8: 0 | K8: 0 | L8: 0 | M8: 0 | N8: 0 | O8: 0 | P8: 0 | Q8: 809 | R8: 0 | S8: =SUM(D8:R8) -> 1781 | X8: =SUM(T8:W8) -> 0 | Y8: 627 | Z8: 215 | AB8: 0 | AC8: 0 | AD8: 0 | AF8: 95819.57 | AH8: Project Budget
B9: FY25/26 | D9: 1091 | E9: 949 | F9: 0 | G9: 780 | H9: 780 | I9: 957 | J9: 0 | K9: 0 | L9: 0 | M9: 0 | N9: 10 | O9: 58 | P9: 358 | Q9: 1393 | R9: 251 | S9: =SUM(D9:R9) -> 6627 | T9: 7778 | U9: 8072 | V9: 0 | W9: 0 | X9: =SUM(T9:W9) -> 15850 | Y9: 4370 | Z9: 27014 | AB9: 0 | AC9: 0 | AD9: 300000 | AF9: 268870.79
B10: FY26/27 | D10: =1575*0.3 -> 472.5 | E10: 0 | F10: 0 | G10: 0 | H10: 0 | I10: 0 | J10: =1575*0.6 -> 945 | K10: =1575*5/12 -> 656.25 | L10: 0 | M10: 0 | N10: 0 | O10: 0 | P10: =1575*0.3 -> 472.5 | Q10: =1575*4/12*0.8 -> 420 | R10: 0 | S10: =SUM(D10:R10) -> 2966.25 | T10: =7778+7907 -> 15685 | U10: =8072+8306 -> 16378 | V10: =15849/2 -> 7924.5 | W10: =15849/2 -> 7924.5 | X10: =SUM(T10:W10) -> 47912 | Y10: 15000 | Z10: 0 | AB10: =((($D10*Rates!$E$25)+($E10*Rates!$E$23)+($F10*Rates!$E$24)+($G10*Rates!$E$23)+($H10*Rates!$J$22)+($I10*Rates!$E$24)+($J10*Rates!$J$23)+($K10*Rates!$J$22)+($L10*Rates!$E$16)+($P10*Rates!$E$23)+($Q10*Rates!$E$23))*Rates!$I$11) -> 227717.24 | AC10: =AB10+X10+Y10+Z10 -> 290629.24 | AD10: 381973.39 | AE10: =AD10-AC10 -> 91344.146 | AF10: 30849.55 | AH10: 1255259.7
B11: FY27/28 | D11: =1575*0.3 -> 472.5 | E11: 0 | F11: 0 | G11: 0 | H11: 0 | I11: 0 | J11: =1575*0.9 -> 1417.5 | K11: 1575 | L11: 0 | M11: 0 | N11: 0 | O11: 0 | P11: =0.1*1575 -> 157.5 | Q11: 0 | R11: 0 | S11: =SUM(D11:R11) -> 3622.5 | T11: =7907+8038.25 -> 15945.25 | U11: =8548+8306 -> 16854 | V11: =(15849/2)+(16212/2) -> 16030.5 | W11: =(15849/2)+(16212/2) -> 16030.5 | X11: =SUM(T11:W11) -> 64860.25 | Y11: 15000 | Z11: 0 | AB11: =((($D11*Rates!$F$25)+($E11*Rates!$F$23)+($F11*Rates!$F$24)+($G11*Rates!$F$23)+($H11*Rates!$K$22)+($I11*Rates!$F$24)+($J11*Rates!$K$23)+($K11*Rates!$K$22)+($L11*Rates!$F$16)+($P11*Rates!$F$23)+($Q11*Rates!$F$23))*Rates!$I$11) -> 301024.42 | AC11: =AB11+X11+Y11+Z11 -> 380884.67 | AD11: 381973.39 | AE11: =AD11-AC11 -> 1088.7203
B12: FY28/29 | D12: =1575*5/12*0.3 -> 196.875 | E12: 0 | F12: 0 | G12: 0 | H12: 0 | I12: 0 | J12: =1575*5/12*0.9 -> 590.625 | K12: =1575*5/12 -> 656.25 | L12: 0 | M12: 0 | N12: 0 | O12: 0 | P12: =1575*5/12*0.1 -> 65.625 | Q12: 0 | R12: 0 | S12: =SUM(D12:R12) -> 1509.375 | T12: =(8038+8172.25)/2 -> 8105.125 | U12: =(8548+8800)/2 -> 8674 | V12: =(16212+16587)/2 -> 16399.5 | W12: =(16212+16587)/2 -> 16399.5 | X12: =SUM(T12:W12) -> 49578.125 | Y12: 7500 | Z12: 0 | AB12: =((($D12*Rates!$G$25)+($E12*Rates!$G$23)+($F12*Rates!$G$24)+($G12*Rates!$G$23)+($H12*Rates!$L$22)+($I12*Rates!$G$24)+($J12*Rates!$L$23)+($K12*Rates!$L$22)+($L12*Rates!$G$16)+($P12*Rates!$G$23)+($Q12*Rates!$G$23))*Rates!$I$11) -> 130443.92 | AC12: =AB12+X12+Y12+Z12 -> 187522.04 | AD12: 95493.35 | AE12: =AD12-AC12 -> -92028.69 | AH12: Forecast Cost at Completion
B14: FAC | D14: =SUM(D8:D13) -> 2256.875 | E14: =SUM(E8:E13) -> 949 | F14: =SUM(F8:F13) -> 0 | G14: =SUM(G8:G13) -> 780 | H14: =SUM(H8:H13) -> 780 | I14: =SUM(I8:I13) -> 1905 | J14: =SUM(J8:J13) -> 2953.125 | K14: =SUM(K8:K13) -> 2887.5 | ... Z14: =SUM(Z8:Z13) -> 27229 | AB14: =SUM(AB8:AB12) -> 659185.58 | AC14: =SUM(AC8:AC12) -> 859035.95 | AD14: =SUM(AD8:AD12) -> 1159440.1 | AF14: =SUM(AF8:AF13) -> 395539.91 | AH14: =(AC10-AF10)+AC11+AC12+AF14 -> 1223726.3
K15: Starts Dec 2026 | Q15: Resigns end July 2026 | Z15: All external spend is on PhDs - no other external spend

Sheet June  26 - UKRI
B1: Project Dashboard- WON 12570-1022 - UKRI
B4: Month | D4: Forecasted Hours | M4: External Forecast | T4: UKRI Cost - Overview
D5: Lloyd Fletcher | E5: Joel Hirst | F5: Joel Hirst | G5: Wiera Bielajewa | H5: Jonathan Horne-Jones | I5: John Charlton | J5: Graduate (TBC) | K5: Christopher Dawson | L5: FC Hours - Total | M5: Travel | N5: External Spend | P5: UKRI Forecast Spend (80% +All expenses) | Q5: UKAEA Shortfall (20%) £401,349 Budget | R5: Total Spend to date - UKRI ONLY
B6: Grade | D6: UKAXI | E6: UKAXE | F6: UKAXG | G6: UKAXE | J6: UKL3 | K6: UKAXE
B7: FY24/25 | D7: 874 | E7: 527 | F7: 0 | G7: 0 | H7: 0 | I7: 570 | J7: 0 | K7: 0 | M7: 642 | N7: 5232 | P7: 0 | Q7: 0 | R7: 116616.82 | T7: Grant Contribution Budget
B8: FY25/26 | D8: 1091 | E8: 949 | F8: 0 | G8: 780 | H8: 7 | I8: 251 | J8: 0 | K8: 1575 | M8: 5048 | N8: 17738 | P8: 0 | Q8: 0 | R8: 211853.97
B9: FY26/27 | D9: =1575*0.6 -> 945 | E9: 0 | F9: 1575 | G9: =1575*0.7 -> 1102.5 | H9: 0 | I9: 0 | J9: 787 | K9: 120 | L9: =SUM(D9:K9) -> 4529.5 | M9: 32492 | N9: 32492 | P9: =((((D9*Rates!$E$25)+('June 26 - UKRI'!F9*Rates!$E$24)+(('June 26 - UKRI'!G9+'June 26 - UKRI'!K9)*Rates!$E$23)+('June 26 - UKRI'!J9*Rates!$E$16))*Rates!$I$11)*0.8)+M9+N9 -> 324242.74 | Q9: =((((E9*Rates!$E$25)+('June 26 - UKRI'!G9*Rates!$E$24)+(('June 26 - UKRI'!H9+'June 26 - UKRI'!L9)*Rates!$E$23)+('June 26 - UKRI'!K9*Rates!$E$16))*Rates!$I$11)*0.2) -> 71705.037 | R9: 43314 | T9: 1605398
B10: FY27/28 | D10: =1575*0.6 -> 945 | E10: 0 | F10: 1575 | G10: =1575*0.7 -> 1102.5 | H10: 0 | I10: 0 | J10: 1575 | K10: 0 | L10: =SUM(D10:K10) -> 5197.5 | M10: 32492 | N10: 32492 | P10: =((((D10*Rates!$F$25)+('June 26 - UKRI'!F10*Rates!$F$24)+(('June 26 - UKRI'!G10+'June 26 - UKRI'!K10)*Rates!$F$23)+('June 26 - UKRI'!J10*Rates!$F$16))*Rates!$I$11)*0.8)+M10+N10 -> 358188.96 | Q10: =((((E10*Rates!$F$25)+('June 26 - UKRI'!G10*Rates!$F$24)+(('June 26 - UKRI'!H10+'June 26 - UKRI'!L10)*Rates!$F$23)+('June 26 - UKRI'!K10*Rates!$F$16))*Rates!$I$11)*0.2) -> 81625.115
B11: FY28/29 | D11: =((1575/12)*3)*0.6 -> 236.25 | E11: 0 | F11: =(1575/12)*3 -> 393.75 | G11: =((1575/12)*3)*0.7 -> 275.625 | H11: 0 | I11: 0 | J11: =(1575/12)*3 -> 393.75 | K11: 0 | L11: =SUM(D11:K11) -> 1299.375 | M11: 29555 | N11: 29555 | P11: =((((D11*Rates!$G$25)+('June 26 - UKRI'!F11*Rates!$G$24)+(('June 26 - UKRI'!G11+'June 26 - UKRI'!K11)*Rates!$G$23)+('June 26 - UKRI'!J11*Rates!$G$16))*Rates!$I$11)*0.8)+M11+N11 -> 135343.29 | Q11: =((((E11*Rates!$G$25)+('June 26 - UKRI'!G11*Rates!$G$24)+(('June 26 - UKRI'!H11+'June 26 - UKRI'!L11)*Rates!$G$23)+('June 26 - UKRI'!K11*Rates!$G$16))*Rates!$I$11)*0.2) -> 21222.53 | T11: Forecast Cost at Completion
B13: FAC | D13: =SUM(D7:D12) -> 4091.25 | E13: =SUM(E7:E12) -> 1476 | F13: =SUM(F7:F12) -> 3543.75 | G13: =SUM(G7:G12) -> 3260.625 | H13: =SUM(H7:H12) -> 7 | I13: =SUM(I7:I12) -> 821 | J13: =SUM(J7:J12) -> 2755.75 | K13: =SUM(K7:K12) -> 1695 | L13: =SUM(L9:L12) -> 11026.375 | M13: =SUM(M7:M12) -> 100229 | N13: =SUM(N7:N12) -> 117509 | P13: =SUM(P7:P11) -> 817774.98 | Q13: =SUM(Q7:Q11) -> 174552.68 | R13: =SUM(R7:R12) -> 371784.79 | T13: =(P13-R9)+R13 -> 1146245.8
T15: Variance
T17: =T9-T13 -> 459152.23

Sheet UKRI
B1: Project Dashboard- WON 12570-1022 - UKRI
B4: Month | D4: Forecasted Hours | Q4: External Forecast | X4: UKRI Cost - Overview
D5: Lloyd Fletcher | E5: Joel Hirst | F5: Joel Hirst | G5: Wiera Bielajewa | H5: Wiera Bielajewa | I5: Jonathan Horne-Jones | J5: John Charlton | K5: Graduates x2 (TBC) | L5: Christopher Dawson | M5: Year In Industry Students | N5: Kiyana Patel | O5: James Panayis | P5: FC Hours - Total | Q5: Travel | R5: External Spend | T5: UKRI Forecast Spend (80% +All expenses) | U5: UKAEA Shortfall (20%) £401,349 Budget | V5: Total Spend to date - UKRI ONLY
B6: Grade | D6: UKAXI | E6: UKAXE | F6: UKAXG | G6: UKAXE | H6: UKAXF | I6: N/A | J6: N/A | K6: UKL3 | L6: UKAXE | M6: N/A | N6: UKAXE | O6: UKAXE
B7: FY24/25 | D7: 874 | E7: 527 | F7: 0 | G7: 0 | H7: 0 | I7: 0 | J7: 570 | K7: 0 | L7: 0 | N7: 0 | O7: 0 | Q7: 642 | R7: 5232 | T7: 0 | U7: 0 | V7: 116616.82 | X7: Grant Contribution Budget
B8: FY25/26 | D8: 1091 | E8: 949 | F8: 0 | G8: 780 | H8: 780 | I8: 7 | J8: 251 | K8: 0 | L8: =1575/2*3/5 -> 472.5 | N8: 0 | O8: 0 | Q8: 5048 | R8: 17738 | T8: 0 | U8: 0 | V8: 211853.97
B9: FY26/27 | D9: =1575*0.6 -> 945 | E9: =1575*6/12 -> 787.5 | F9: =1575*6/12 -> 787.5 | G9: =1575*6/12*0.7 -> 551.25 | H9: =1575*6/12*0.7 -> 551.25 | I9: 0 | J9: 0 | K9: =787*2 -> 1574 | L9: =1575*6/12*3/5 -> 472.5 | M9: =2*1575*9/12 -> 2362.5 | N9: =1575*6/12*0.6 -> 472.5 | O9: =1575*8/12*0.4 -> 420 | P9: =SUM(D9:O9) -> 8924 | Q9: 6000 | R9: 20000 | T9: =(((((D9*Rates!$E$25)+(UKRI!E9*Rates!$E$23)+(UKRI!F9*Rates!$E$24)+(UKRI!G9*Rates!$E$23)+(UKRI!H9*Rates!$J$22)+(UKRI!K9*Rates!$E$16)+(UKRI!L9*Rates!$E$23)+(UKRI!M9*Rates!$J$25)+(UKRI!N9*Rates!$E$23)+(UKRI!O9*Rates!$E$23))*Rates!$I$11)+Q9+R9)*0.8) -> 398812.05 | U9: =T9/0.8*0.2 -> 99703.013 | V9: 43314 | X9: 1605398
B10: FY27/28 | D10: =1575*0.6 -> 945 | E10: 0 | F10: 1575 | G10: 0 | H10: 1575 | I10: 0 | J10: 0 | K10: =1575*2 -> 3150 | L10: 0 | M10: =2*1575*3/12 -> 787.5 | N10: 0 | O10: 0 | P10: =SUM(D10:O10) -> 8032.5 | Q10: 6000 | R10: 20000 | T10: =(((((D10*Rates!$F$25)+(UKRI!E10*Rates!$F$23)+(UKRI!F10*Rates!$F$24)+(UKRI!G10*Rates!$F$23)+(UKRI!H10*Rates!$K$22)+(UKRI!K10*Rates!$F$16)+(UKRI!L10*Rates!$F$23)+(UKRI!M10*Rates!$K$25)+(UKRI!N10*Rates!$F$23)+(UKRI!O10*Rates!$F$23))*Rates!$I$11)+Q10+R10)*0.8) -> 422839.73 | U10: =T10/0.8*0.2 -> 105709.93
B11: FY28/29 | D11: =1575*5/12*0.6 -> 393.75 | E11: 0 | F11: =1575*5/12 -> 656.25 | G11: 0 | H11: =1575*5/12 -> 656.25 | I11: 0 | J11: 0 | K11: =1575*5/12*2 -> 1312.5 | M11: 0 | N11: 0 | O11: 0 | P11: =SUM(D11:O11) -> 3018.75 | Q11: 6000 | R11: 20000 | T11: =(((((D11*Rates!$G$25)+(UKRI!E11*Rates!$G$23)+(UKRI!F11*Rates!$G$24)+(UKRI!G11*Rates!$G$23)+(UKRI!H11*Rates!$I$22)+(UKRI!K11*Rates!$G$16)+(UKRI!L11*Rates!$G$23)+(UKRI!M10*Rates!$L$25)+(UKRI!N11*Rates!$G$23)+(UKRI!O11*Rates!$G$23))*Rates!$I$11)+Q11+R11)*0.8) -> 199097.59 | U11: =T11/0.8*0.2 -> 49774.397 | X11: Forecast Cost at Completion
B13: FAC | D13: =SUM(D7:D12) -> 4248.75 | E13: =SUM(E7:E12) -> 2263.5 | F13: =SUM(F7:F12) -> 3018.75 | G13: =SUM(G7:G12) -> 1331.25 | H13: =SUM(H7:H12) -> 3562.5 | I13: =SUM(I7:I12) -> 7 | J13: =SUM(J7:J12) -> 821 | K13: =SUM(K7:K12) -> 6036.5 | ... O13: =SUM(O7:O12) -> 420 | P13: =SUM(P9:P12) -> 19975.25 | Q13: =SUM(Q7:Q12) -> 23690 | R13: =SUM(R7:R12) -> 82970 | T13: =SUM(T7:T11) -> 1020749.4 | U13: =SUM(U7:U11) -> 255187.34 | V13: =SUM(V7:V12) -> 371784.79 | X13: =(T13-V9)+V13 -> 1349220.2
X15: Variance
U16: FY 26/27
D17: Fixed Issues Reducing Variance | T17: Year in Industry | U17: J25 | X17: =X9-X13 -> 256177.84
D18: 1 | E18: Last year of UKRI FLF is until end of Aug so 5 months, not 3 months - fixing this drastically reduced variance | T18: UKAXF | U18: J22
D19: 2 | E19: Intermediate grades costed lower: UKAXF costed at UKM4 rate, fixed to be halfway between for UKAXF and UKAXH | T19: UKAXH | U19: J23
D20: 3 | E20: Year in industry students not costed for
U21: FY 26/27
D22: Updated based on new information | T22: UKL3 | U22: E16
D23: 1 | E23: Adel -> H after appeal | T23: UKM3 | U23: E22
D24: 2 | E24: Alex's resignation date and Rob's starting date accounted for on UKAEA sheet | T24: UKM4 | U24: E23
D25: 3 | E25: Adjusted travel and external spend costs based on FY 25/26 actual expenditure | T25: UKM5 | U25: E24
D26: 4 | E26: No external spend other than PhDs on UKAEA code | T26: UKM6 | U26: E25
D27: 5 | E27: Promotions for Joel/Wiera corrected based on projected dates
T28: 26/27 | U28: E | V28: J
T29: 27/28 | U29: F | V29: K
T30: 28/29 | U30: G | V30: L
